py3_database/__init__.py
py3_database/mysql/__init__.py
py3_database/mysql/pymysql.py
py3_database/sqlite/__init__.py
py3_database/sqlite/sqlite3.py
py3_database-1.0.4.dist-info/LICENSE
py3_database-1.0.4.dist-info/METADATA
py3_database-1.0.4.dist-info/WHEEL
py3_database-1.0.4.dist-info/top_level.txt
py3_database-1.0.4.dist-info/RECORD
