Metadata-Version: 2.1
Name: py3-database
Version: 1.0.4
Summary: The Python3 Database Library Developed By Guolei
Home-page: https://github.com/guolei19850528/py3_database
Author: guolei
Author-email: 174000902@qq.com
License: MIT
Requires-Python: >=3.0
License-File: LICENSE
Requires-Dist: PyMySQL
Requires-Dist: redis
Requires-Dist: duckdb
Requires-Dist: diskcache
Requires-Dist: addict
Requires-Dist: retrying
Requires-Dist: jsonschema
Requires-Dist: retrying
Requires-Dist: setuptools
Requires-Dist: wheel
